[
  {
    "name": "users",
    "columns": [
      {
        "id": "userId",
        "name": "User ID",
        "type": "NUMBER",
        "primary": true,
        "filter": true
      },
      { "id": "name", "name": "Name", "type": "STRING", "filter": true },
      {
        "id": "roleCode",
        "name": "Role Code",
        "type": "STRING",
        "referenceTable": "roles",
        "enum": ["maintainer", "developer"]
      },
      {
        "id": "maleOrFemale",
        "name": "Male or Female",
        "type": "STRING",
        "type:createUpdatePage": "RadioGroup",
        "enum": ["male", "female"]
      },
      { "id": "age", "name": "Age", "type": "NUMBER" },
      { "id": "active", "name": "Active", "type": "BOOL" },
      { "id": "tags", "name": "Tags", "type": "STRING_ARRAY" },
      {
        "id": "notes",
        "name": "Notes",
        "type": "STRING",
        "type:createUpdatePage": "TextArea"
      }
    ],
    "large": true
  },
  {
    "name": "roles",
    "columns": [
      {
        "id": "code",
        "name": "Code",
        "type": "STRING",
        "primary": true
      },
      { "id": "name", "name": "Name", "type": "STRING" }
    ]
  }
]
